Metadata-Version: 2.4
Name: tfver
Version: 1.1.1
Summary: Fetches metadata from Terraform releases
Author-email: Ryan Hansohn <info@imnorobot.com>
Maintainer-email: Ryan Hansohn <info@imnorobot.com>
License-Expression: MIT AND (Apache-2.0 OR BSD-2-Clause)
Project-URL: Source, https://github.com/hansohn/tfver
Project-URL: Tracker, https://github.com/hansohn/tfver/issues
Keywords: terraform,release
Classifier: Intended Audience :: Developers
Classifier: Intended Audience :: System Administrators
Classifier: Programming Language :: Python :: 3
Requires-Python: >=3.8
License-File: LICENSE
Requires-Dist: click
Requires-Dist: packaging
Requires-Dist: pyyaml
Requires-Dist: requests
Requires-Dist: semver
Requires-Dist: typing
Dynamic: license-file
